tests/__init__.py
tgr/__init__.py
tgr/birefringence.py
tgr/dipole.py
tgr/fta.py
tgr/lineofsight.py
tgr/massivegraviton.py
tgr/ppe.py
tgr-0.1.0.dist-info/LICENSE
tgr-0.1.0.dist-info/METADATA
tgr-0.1.0.dist-info/WHEEL
tgr-0.1.0.dist-info/entry_points.txt
tgr-0.1.0.dist-info/top_level.txt
tgr-0.1.0.dist-info/RECORD
