Metadata-Version: 2.1
Name: tgr
Version: 0.1.0
Summary: Testing General Relativity with Gravitational Waves
Author-email: Yifan Wang <yifan.wang@aei.mpg.de>
Project-URL: Homepage, https://github.com/yi-fan-wang/TestingGR_with_Gravwaves
Project-URL: Issues, https://github.com/yi-fan-wang/TestingGR_with_Gravwaves/issues
Classifier: Programming Language :: Python :: 3
Classifier: License :: OSI Approved :: MIT License
Classifier: Operating System :: OS Independent
Requires-Python: >=3.8
License-File: LICENSE
Requires-Dist: pycbc
